Metadata-Version: 2.1
Name: odoo-addon-stock_picking_completion_info
Version: 18.0.1.0.0.2
Requires-Python: >=3.10
Requires-Dist: odoo-addon-stock_move_common_dest==18.0.*
Requires-Dist: odoo==18.0.*
Summary: Display on current document completion information according to next operations
Home-page: https://github.com/OCA/stock-logistics-warehouse
License: AGPL-3
Author: Camptocamp, Odoo Community Association (OCA)
Author-email: support@odoo-community.org
Classifier: Programming Language :: Python
Classifier: Framework :: Odoo
Classifier: Framework :: Odoo :: 18.0
Classifier: License :: OSI Approved :: GNU Affero General Public License v3
Classifier: Development Status :: 4 - Beta
